LICENSE
MANIFEST.in
README.rst
setup.cfg
setup.py
django_genetics.egg-info/PKG-INFO
django_genetics.egg-info/SOURCES.txt
django_genetics.egg-info/dependency_links.txt
django_genetics.egg-info/requires.txt
django_genetics.egg-info/top_level.txt
genetics/__init__.py
genetics/admin.py
genetics/api.py
genetics/apps.py
genetics/forms.py
genetics/models.py
genetics/tests.py
genetics/urls.py
genetics/utils.py
genetics/views.py
genetics/data/hgnc/HGNC Gene w alias.csv
genetics/data/hgnc/HGNC Gene.csv
genetics/data/omim/mimTitles.csv
genetics/data/omim/morbidmap.csv
genetics/management/commands/import_gene.py
genetics/migrations/0001_initial.py
genetics/migrations/__init__.py
genetics/static/css/genetics.css
genetics/static/js/genetics.js
genetics/templates/genetics/widgets/attrs.html
genetics/templates/genetics/widgets/gene.html
genetics/templates/genetics/widgets/sequence_variant.html
genetics/templates/genetics/widgets/sequence_variant_from_gene.html